.gitignore
.gitlab-ci.yml
CHANGELOG.md
CMakeLists.txt
COPYING
INSTALL
LICENSE.md
README.md
config.h.cmake
dune-localfunctions.pc.in
dune.module
pyproject.toml
setup.py
LICENSES/LicenseRef-GPL-2.0-only-with-DUNE-exception.txt
doc/CMakeLists.txt
doc/dune-localfunctions-manual.tex
doc/doxygen/CMakeLists.txt
doc/doxygen/Doxylocal
doc/doxygen/mainpage.txt
doc/doxygen/modules.txt
dune/CMakeLists.txt
dune/localfunctions/CMakeLists.txt
dune/localfunctions/brezzidouglasmarini.hh
dune/localfunctions/crouzeixraviart.hh
dune/localfunctions/dualmortarbasis.hh
dune/localfunctions/enriched.hh
dune/localfunctions/hierarchical.hh
dune/localfunctions/lagrange.hh
dune/localfunctions/mimetic.hh
dune/localfunctions/monomial.hh
dune/localfunctions/nedelec.hh
dune/localfunctions/orthonormal.hh
dune/localfunctions/rannacherturek.hh
dune/localfunctions/raviartthomas.hh
dune/localfunctions/refined.hh
dune/localfunctions/brezzidouglasfortinmarini/CMakeLists.txt
dune/localfunctions/brezzidouglasfortinmarini/bdfmcube.hh
dune/localfunctions/brezzidouglasfortinmarini/cube/CMakeLists.txt
dune/localfunctions/brezzidouglasfortinmarini/cube/localbasis.hh
dune/localfunctions/brezzidouglasfortinmarini/cube/localcoefficients.hh
dune/localfunctions/brezzidouglasfortinmarini/cube/localinterpolation.hh
dune/localfunctions/brezzidouglasmarini/CMakeLists.txt
dune/localfunctions/brezzidouglasmarini/brezzidouglasmarini1cube2d.hh
dune/localfunctions/brezzidouglasmarini/brezzidouglasmarini1cube3d.hh
dune/localfunctions/brezzidouglasmarini/brezzidouglasmarini1simplex2d.hh
dune/localfunctions/brezzidouglasmarini/brezzidouglasmarini2cube2d.hh
dune/localfunctions/brezzidouglasmarini/brezzidouglasmarini2simplex2d.hh
dune/localfunctions/brezzidouglasmarini/brezzidouglasmarinicube.hh
dune/localfunctions/brezzidouglasmarini/brezzidouglasmarinisimplex.hh
dune/localfunctions/brezzidouglasmarini/brezzidouglasmarini1cube2d/CMakeLists.txt
python/dune_localfunctions.egg-info/PKG-INFO
python/dune_localfunctions.egg-info/SOURCES.txt
python/dune_localfunctions.egg-info/dependency_links.txt
python/dune_localfunctions.egg-info/requires.txt
python/dune_localfunctions.egg-info/top_level.txt